MANIFEST.in
setup.py
src/me2/__init__.py
src/me2/common/__init__.py
src/me2/common/util.py
src/me2/server/__init__.py
src/me2/server/bundle_manager.py
src/me2/server/container.py
src/me2/server/daemon.py
src/me2/server/execution_manager.py
src/me2/server/storage_manager.py
src/me2/server/util.py
src/me2/server/apps/__init__.py
src/me2/server/apps/mded.py
src/me2/server/data/package_install_init.mak
src/me2/server/lxc/__init__.py
src/me2/server/lxc/execution_manager.py
src/me2/server/lxc/data/lxc_init.mak
src/me2/server/lxc/data/templates/lxc_config.mak
src/me2/server/lxc/data/templates/lxc_fstab.mak
src/me2/server/tests/__init__.py
src/me2/server/web/__init__.py
src/me2/server/web/server.py
src/me2/server/web/templates/base.html
src/me2/server/web/templates/bottles.html
src/me2/server/web/templates/template.html
src/me2/server/web/templates/static/css/bootstrap-responsive.css
src/me2/server/web/templates/static/css/bootstrap-responsive.min.css
src/me2/server/web/templates/static/css/bootstrap.css
src/me2/server/web/templates/static/css/bootstrap.min.css
src/me2/server/web/templates/static/img/glyphicons-halflings-white.png
src/me2/server/web/templates/static/img/glyphicons-halflings.png
src/me2/server/web/templates/static/js/bootstrap.js
src/me2/server/web/templates/static/js/bootstrap.min.js
src/me2/server/web/templates/static/js/me2.js
src/me2_supervisor.egg-info/PKG-INFO
src/me2_supervisor.egg-info/SOURCES.txt
src/me2_supervisor.egg-info/dependency_links.txt
src/me2_supervisor.egg-info/entry_points.txt
src/me2_supervisor.egg-info/namespace_packages.txt
src/me2_supervisor.egg-info/requires.txt
src/me2_supervisor.egg-info/top_level.txt