Metadata-Version: 1.1
Name: me2-supervisor
Version: 0.0.9
Summary: me2 is a mOSAIC Cloud Project component responsible for the deployment and supervision of application
Home-page: http://developers.mosaic-cloud.eu
Author: Marian Neagul
Author-email: marian@ieat.ro
License: APL
Keywords: deployment mosaic
Platform: UNKNOWN
Classifier: Intended Audience :: Developers
Classifier: Development Status :: 3 - Alpha
Classifier: Topic :: System :: Installation/Setup
Classifier: License :: OSI Approved :: Apache Software License
